oomnitza_events/__init__.py
oomnitza_events/connectors.py
oomnitza_events/constants.py
oomnitza_events/errors.py
oomnitza_events/events.py
oomnitza_events/schemas.py
oomnitza_events/trackers.py
oomnitza_events/utils.py
oomnitza_events/version.py
oomnitza_events-0.1.2.dist-info/METADATA
oomnitza_events-0.1.2.dist-info/WHEEL
oomnitza_events-0.1.2.dist-info/top_level.txt
oomnitza_events-0.1.2.dist-info/RECORD
