Metadata-Version: 2.1
Name: oomnitza-events
Version: 0.1.2
Summary: This project is developed for tracking Oomnitza activities.
Author: Oomnitza
Author-email: etl-admin@oomnitza.com
Requires-Dist: analytics-python ==1.2.9
Requires-Dist: arrow
Requires-Dist: Cerberus
Requires-Dist: psycopg2-binary ==2.9.9
Requires-Dist: typing-extensions
Provides-Extra: dev
Requires-Dist: pytest ; extra == 'dev'
Requires-Dist: pytest-pep8 ; extra == 'dev'
Requires-Dist: pytest-cov ; extra == 'dev'
Requires-Dist: wheel ; extra == 'dev'
